README.md
setup.py
linkedin_scrape_comments/__init__.py
linkedin_scrape_comments.egg-info/PKG-INFO
linkedin_scrape_comments.egg-info/SOURCES.txt
linkedin_scrape_comments.egg-info/dependency_links.txt
linkedin_scrape_comments.egg-info/requires.txt
linkedin_scrape_comments.egg-info/top_level.txt