Metadata-Version: 2.1
Name: linkedin-scrape-comments
Version: 1.0.0
Summary: A python library to scrape post comments data from linkedin automatically.
Home-page: https://linkedin-api.datakund.com/en/latest/
Author: DataKund
Author-email: datakund@gmail.com
License: Apache License 2.0
Keywords: linkedin python bot_studio scraper post comments data web-scraping
Platform: UNKNOWN
